adslab/1.txt
adslab/2.txt
adslab/3.txt
adslab/__init__.py
adslab/get_exp.py
adslab-0.0.5.dist-info/LICENSE
adslab-0.0.5.dist-info/METADATA
adslab-0.0.5.dist-info/WHEEL
adslab-0.0.5.dist-info/top_level.txt
adslab-0.0.5.dist-info/RECORD
