Metadata-Version: 2.1
Name: adslab
Version: 0.0.5
Summary: Package for learning ads experiements
Author-email: Vettai mannan <vettaimanan07@gmail.com>
Classifier: Programming Language :: Python :: 3
Classifier: License :: OSI Approved :: MIT License
Classifier: Operating System :: OS Independent
Requires-Python: >=3.7
License-File: LICENSE
